mdbl/__init__.py
mdbl/mdbl.py
mdbl-1.0.8.dist-info/METADATA
mdbl-1.0.8.dist-info/RECORD
mdbl-1.0.8.dist-info/WHEEL
mdbl-1.0.8.dist-info/top_level.txt
